./.gitignore
./LICENSE
./PKG-INFO
./README.md
./__init__.py
./feed2json.py
./pyproject.toml
./requirements.text
./test_feed2json.py
./.github/FUNDING.yml
./.github/workflows/python-publish.yml
feed2json-2025.7.15.dist-info/METADATA
feed2json-2025.7.15.dist-info/WHEEL
feed2json-2025.7.15.dist-info/licenses/LICENSE
feed2json-2025.7.15.dist-info/RECORD
