Metadata-Version: 2.4
Name: feed2json
Version: 2025.7.15
Summary: Convert RSS feed to JSON Feed
Project-URL: Homepage, https://github.com/versun/feed2json
Project-URL: Repository, https://github.com/versun/feed2json.git
Project-URL: Issues, https://github.com/versun/feed2json/issues
Author-email: Versun <feed2json@versun.me>
License: MIT License
License-File: LICENSE
Classifier: Environment :: Web Environment
Classifier: Intended Audience :: Developers
Classifier: License :: OSI Approved :: MIT License
Classifier: Operating System :: OS Independent
Classifier: Programming Language :: Python
Classifier: Programming Language :: Python :: 3
Classifier: Programming Language :: Python :: 3 :: Only
Classifier: Programming Language :: Python :: 3.10
Classifier: Programming Language :: Python :: 3.11
Classifier: Programming Language :: Python :: 3.12
Classifier: Topic :: Software Development :: Libraries :: Python Modules
Requires-Python: >=3.10
Requires-Dist: feedparser>=6.0.11
Requires-Dist: pytest>=8.4.1
